spoti_stream/__init__.py
spoti_stream/__main__.py
spoti_stream/converter.py
spoti_stream/downloader.py
spoti_stream/install_dependencies.py
spoti_stream/spotify_utils.py
spoti_stream-1.1.dist-info/LICENSE.txt
spoti_stream-1.1.dist-info/METADATA
spoti_stream-1.1.dist-info/WHEEL
spoti_stream-1.1.dist-info/entry_points.txt
spoti_stream-1.1.dist-info/top_level.txt
spoti_stream-1.1.dist-info/RECORD
