Metadata-Version: 2.1
Name: spoti_stream
Version: 1.1
Summary: A tool to download Spotify playlist songs using YouTube
Home-page: https://github.com/mehmoodulhaq570/SpotiStream
Author: Mehmood Ul Haq
Author-email: mehmoodulhaq1040@gmail.com
License: MIT
Project-URL: Documentation, https://github.com/mehmoodulhaq570/SpotiStream#readme
Project-URL: Source, https://github.com/mehmoodulhaq570/SpotiStream
Project-URL: Bug Tracker, https://github.com/mehmoodulhaq570/SpotiStream/issues
Classifier: Programming Language :: Python :: 3
Classifier: License :: OSI Approved :: MIT License
Classifier: Operating System :: OS Independent
Requires-Python: >=3.6
License-File: LICENSE.txt
Requires-Dist: spotipy >=2.19.0
Requires-Dist: yt-dlp >=2021.12.1
Requires-Dist: moviepy >=1.0.3
Requires-Dist: pydub >=0.25.1
